etlops/__init__.py
etlops/utils.py
etlops/clients/__init__.py
etlops/clients/awss3.py
etlops/clients/cloudstorage.py
etlops/clients/exceptions.py
etlops/clients/gcpstorage.py
etlops/clients/mpp.py
etlops/clients/rdbms.py
etlops/clients/sql.py
etlops/databaseops/__init__.py
etlops/databaseops/abstracts.py
etlops/databaseops/mysql.py
etlops/databaseops/snowflake.py
etlops/streams/__init__.py
tests/__init__.py
tests/integration/__init__.py
tests/integration/test_AWSS3.py
tests/integration/test_GCPStorage.py
tests/integration/test_MySQLQuerySequence.py
tests/integration/test_snowflake_client.py
tests/integration/test_snowflake_client_warehouses.py
tests/integration/test_assets/__init__.py
tests/integration/test_assets/constants.py
tests/unit/__init__.py
tests/unit/db_client_utils.py
tests/unit/test_MySQLClient.py
tests/unit/test_SnowflakeClient.py
etlops-0.1.1.dist-info/LICENSE
etlops-0.1.1.dist-info/METADATA
etlops-0.1.1.dist-info/WHEEL
etlops-0.1.1.dist-info/top_level.txt
etlops-0.1.1.dist-info/RECORD
