Metadata-Version: 2.1
Name: etlops
Version: 0.1.1
Summary: ETL Operations
Home-page: https://github.com/pypa/example-project
Author: Seriously Analytics Team
Author-email: carlosvalde9@gmail.com
License: UNKNOWN
Platform: UNKNOWN
Classifier: Programming Language :: Python :: 3
Classifier: License :: OSI Approved :: MIT License
Classifier: Operating System :: OS Independent
Requires-Dist: retrying (==1.3.3)
Requires-Dist: pandas (>=0.25.1)
Provides-Extra: all_extras
Requires-Dist: black ; extra == 'all_extras'
Requires-Dist: pytest (>=5.0) ; extra == 'all_extras'
Requires-Dist: pytest-cov (>=2.6) ; extra == 'all_extras'
Requires-Dist: pytest-env (>=0.6.0) ; extra == 'all_extras'
Requires-Dist: pytest-dotenv (>=0.5.0) ; extra == 'all_extras'
Requires-Dist: google-cloud-storage ; extra == 'all_extras'
Requires-Dist: mysql-connector-python (>=8.0.17) ; extra == 'all_extras'
Requires-Dist: SQLAlchemy (>=1.3.8) ; extra == 'all_extras'
Requires-Dist: boto3 ; extra == 'all_extras'
Requires-Dist: snowflake-connector-python (>=1.9.0) ; extra == 'all_extras'
Requires-Dist: snowflake-sqlalchemy (>=1.1.14) ; extra == 'all_extras'
Provides-Extra: dev
Requires-Dist: black ; extra == 'dev'
Requires-Dist: pytest (>=5.0) ; extra == 'dev'
Requires-Dist: pytest-cov (>=2.6) ; extra == 'dev'
Requires-Dist: pytest-env (>=0.6.0) ; extra == 'dev'
Requires-Dist: pytest-dotenv (>=0.5.0) ; extra == 'dev'
Provides-Extra: gcs
Requires-Dist: google-cloud-storage ; extra == 'gcs'
Provides-Extra: mysql
Requires-Dist: mysql-connector-python (>=8.0.17) ; extra == 'mysql'
Requires-Dist: SQLAlchemy (>=1.3.8) ; extra == 'mysql'
Provides-Extra: s3
Requires-Dist: boto3 ; extra == 's3'
Provides-Extra: snowflake
Requires-Dist: snowflake-connector-python (>=1.9.0) ; extra == 'snowflake'
Requires-Dist: snowflake-sqlalchemy (>=1.1.14) ; extra == 'snowflake'
Requires-Dist: SQLAlchemy (>=1.3.8) ; extra == 'snowflake'
Provides-Extra: test
Requires-Dist: pytest (>=5.0) ; extra == 'test'
Requires-Dist: pytest-cov (>=2.6) ; extra == 'test'
Requires-Dist: pytest-env (>=0.6.0) ; extra == 'test'
Requires-Dist: pytest-dotenv (>=0.5.0) ; extra == 'test'
